ytb_gears/__init__.py
ytb_gears/client.py
ytb_gears/uploader.py
ytb_gears-0.6.0.dist-info/METADATA
ytb_gears-0.6.0.dist-info/WHEEL
ytb_gears-0.6.0.dist-info/RECORD
