Metadata-Version: 2.4
Name: ytb-gears
Version: 0.6.0
Summary: A Python package to interact with YouTube Data API v3.
Author-email: Hao Guan <10684225+hguandl@users.noreply.github.com>
Requires-Python: >=3.9
Requires-Dist: google-api-python-client>=2.158.0
Requires-Dist: google-auth-oauthlib>=1.2.1
Provides-Extra: test
Requires-Dist: tqdm>=4.67.1; extra == 'test'
